systool/__init__.py
systool/data.py
systool/distribution.py
systool/geo.py
systool/linreg.py
systool/plot.py
systool/utils/__init__.py
systool/utils/charts.py
systool/utils/flatt_geom.py
systool/utils/get_ftp_data.py
systool/utils/get_socioEconomic_data.py
systool/utils/linear_regression_make.py
systool/utils/linear_regression_plot.py
systool/utils/maps.py
systool/utils/miscFunctions.py
systool/utils/readWrite.py
systool/utils/report.py
systool-0.6.5.dist-info/LICENSE.txt
systool-0.6.5.dist-info/METADATA
systool-0.6.5.dist-info/WHEEL
systool-0.6.5.dist-info/top_level.txt
systool-0.6.5.dist-info/RECORD
