Metadata-Version: 2.1
Name: systool
Version: 0.6.5
Summary: Set of high level funcions that optimize our work as transport planners. Should work along with spyder=5.4.4
Home-page: https://github.com/bruna-calazans/systools
Author: Bruna Calazans (bruna-calazans) & Pedro Chiachio (pcardoso-sk)
Author-email: bcalazans@systra.com
License: MIT
Keywords: systool,engenharia,transportes,systra,engenharia de transportes
License-File: LICENSE.txt
Requires-Dist: pytest (==7.2.2)
Requires-Dist: pandas (==1.5.3)
Requires-Dist: numpy (==1.24.2)
Requires-Dist: matplotlib (==3.7.1)
Requires-Dist: matplotlib-scalebar (==0.8.1)
Requires-Dist: pyqt5 (==5.15.9)
Requires-Dist: geopandas (==0.12.2)
Requires-Dist: openpyxl (==3.1.2)
Requires-Dist: seaborn (==0.12.2)
Requires-Dist: statsmodels (==0.13.5)
Requires-Dist: spyder (==5.4.4)
Requires-Dist: tqdm (==4.65.0)
Requires-Dist: scipy (==1.10.1)
Requires-Dist: plotly (==5.13.1)
Requires-Dist: shapely (==2.0.1)
